{
  "unversionedId": "api/OnContentError",
  "id": "api/OnContentError",
  "title": "OnContentError",
  "description": "Type: TSInterface",
  "source": "@site/docs/api/OnContentError.mdx",
  "sourceDirName": "api",
  "slug": "/api/OnContentError",
  "permalink": "/egjs-infinitegrid/docs/next/api/OnContentError",
  "draft": false,
  "editUrl": null,
  "tags": [],
  "version": "current",
  "frontMatter": {
    "custom_edit_url": null
  },
  "sidebar": "api",
  "previous": {
    "title": "OnRenderComplete",
    "permalink": "/egjs-infinitegrid/docs/next/api/OnRenderComplete"
  },
  "next": {
    "title": "OnChangeScroll",
    "permalink": "/egjs-infinitegrid/docs/next/api/OnChangeScroll"
  }
}