{
  "unversionedId": "api/OnChangeScroll",
  "id": "version-4.0.0/api/OnChangeScroll",
  "title": "OnChangeScroll",
  "description": "OnChangeScroll",
  "source": "@site/i18n/ko/docusaurus-plugin-content-docs/version-4.0.0/api/OnChangeScroll.mdx",
  "sourceDirName": "api",
  "slug": "/api/OnChangeScroll",
  "permalink": "/egjs-infinitegrid/ko/docs/4.0.0/api/OnChangeScroll",
  "draft": false,
  "editUrl": null,
  "tags": [],
  "version": "4.0.0",
  "frontMatter": {
    "custom_edit_url": null
  },
  "sidebar": "version-4.0.0/api",
  "previous": {
    "title": "OnContentError",
    "permalink": "/egjs-infinitegrid/ko/docs/4.0.0/api/OnContentError"
  }
}